extended_tortoise_models/__init__.py
extended_tortoise_models-0.1.2.dist-info/WHEEL
extended_tortoise_models-0.1.2.dist-info/METADATA
extended_tortoise_models-0.1.2.dist-info/RECORD
